streamlit-plotly-events2/__init__.py
streamlit-plotly-events2/example.py
streamlit-plotly-events2/frontend/build/asset-manifest.json
streamlit-plotly-events2/frontend/build/bootstrap.min.css
streamlit-plotly-events2/frontend/build/index.html
streamlit-plotly-events2/frontend/build/static/js/main.42cfd9cb.js
streamlit-plotly-events2/frontend/build/static/js/main.42cfd9cb.js.LICENSE.txt
streamlit-plotly-events2/frontend/build/static/js/main.42cfd9cb.js.map
streamlit_plotly_events2/__init__.py
streamlit_plotly_events2/example.py
streamlit_plotly_events2/frontend/build/asset-manifest.json
streamlit_plotly_events2/frontend/build/bootstrap.min.css
streamlit_plotly_events2/frontend/build/index.html
streamlit_plotly_events2/frontend/build/static/js/main.42cfd9cb.js
streamlit_plotly_events2/frontend/build/static/js/main.42cfd9cb.js.LICENSE.txt
streamlit_plotly_events2/frontend/build/static/js/main.42cfd9cb.js.map
streamlit_plotly_events2-0.0.7.dist-info/LICENSE
streamlit_plotly_events2-0.0.7.dist-info/METADATA
streamlit_plotly_events2-0.0.7.dist-info/WHEEL
streamlit_plotly_events2-0.0.7.dist-info/top_level.txt
streamlit_plotly_events2-0.0.7.dist-info/RECORD
