Metadata-Version: 2.1
Name: streamlit-plotly-events2
Version: 0.0.7
Summary: Reviving the Streamlit community package, streamlit-plotly-events
Home-page: https://github.com/malariagen/streamlit-plotly-events2
Author: Chiyun Lee
Author-email: chiyun.alberto.lee@gmail.com
Requires-Python: >=3.10
License-File: LICENSE
Requires-Dist: streamlit >=1.36
Provides-Extra: devel
Requires-Dist: wheel ; extra == 'devel'
Requires-Dist: pytest ==7.4.0 ; extra == 'devel'
Requires-Dist: playwright ==1.39.0 ; extra == 'devel'
Requires-Dist: requests ==2.31.0 ; extra == 'devel'
Requires-Dist: pytest-playwright-snapshot ==1.0 ; extra == 'devel'
Requires-Dist: pytest-rerunfailures ==12.0 ; extra == 'devel'
